wepipe/.DS_Store
wepipe/__init__.py
wepipe/_version.py
wepipe/core/.DS_Store
wepipe/core/configuration.py
wepipe/core/payload.py
wepipe/core/process_workflow.py
wepipe/core/processor.py
wepipe/core/workflow/__init__.py
wepipe/core/workflow/base_store.py
wepipe/core/workflow/store.py
wepipe/core/workflow/workflow.py
wepipe/destination/__init__.py
wepipe/destination/base_destination.py
wepipe/destination/logger_destination.py
wepipe/destination/pandas_destination.py
wepipe/destination/streamlit_chart_destination.py
wepipe/integrate/.DS_Store
wepipe/integrate/__init__.py
wepipe/integrate/gpu_util.py
wepipe/integrate/postprocessor/__init__.py
wepipe/integrate/postprocessor/base_postprocessor.py
wepipe/integrate/postprocessor/inference_aggregator.py
wepipe/integrate/postprocessor/inference_aggregator_function.py
wepipe/integrate/preprocessor/__init__.py
wepipe/integrate/preprocessor/base_preprocessor.py
wepipe/integrate/preprocessor/text_cleaner.py
wepipe/integrate/preprocessor/text_cleaning_function.py
wepipe/integrate/preprocessor/text_splitter.py
wepipe/integrate/preprocessor/text_tokenizer.py
wepipe/integrate/scrapper/web_search.py
wepipe/integrate/scrapper/youtube_reviews_scrapper.py
wepipe/integrate/utils.py
wepipe/pipeline/.DS_Store
wepipe/pipeline/altair/__init__.py
wepipe/pipeline/altair/client.py
wepipe/pipeline/altair/lineplot_pipeline.py
wepipe/pipeline/base_pipeline.py
wepipe/pipeline/dummy_pipeline.py
wepipe/pipeline/huggingface/__init__.py
wepipe/pipeline/huggingface/classification_pipeline.py
wepipe/pipeline/huggingface/ner_pipeline.py
wepipe/pipeline/huggingface/sentiment_pipeline.py
wepipe/pipeline/huggingface/translation_pipeline.py
wepipe/source/__init__.py
wepipe/source/appstore_scrapper_source.py
wepipe/source/base_source.py
wepipe/source/pandas_source.py
wepipe/source/reddit_scrapper_source.py
wepipe/source/youtube_scrapper_source.py
wepipe-0.1.3.dist-info/LICENSE
wepipe-0.1.3.dist-info/WHEEL
wepipe-0.1.3.dist-info/METADATA
wepipe-0.1.3.dist-info/RECORD
